setup.py
pytest_blocker/__init__.py
pytest_blocker/__version__.py
pytest_blocker.egg-info/PKG-INFO
pytest_blocker.egg-info/SOURCES.txt
pytest_blocker.egg-info/dependency_links.txt
pytest_blocker.egg-info/entry_points.txt
pytest_blocker.egg-info/requires.txt
pytest_blocker.egg-info/top_level.txt